inflector/__init__.py
inflector/src/__init__.py
inflector/src/inflector.py
inflector/src/utils.py
inflector/src/rules/__init__.py
inflector/src/rules/base.py
inflector/src/rules/english.py
inflector/src/rules/spanish.py
inflector/tests/__init__.py
inflector/tests/tests.py
inflector/tests/tests_es.py
python_inflector-0.0.12.dist-info/LICENSE
python_inflector-0.0.12.dist-info/METADATA
python_inflector-0.0.12.dist-info/WHEEL
python_inflector-0.0.12.dist-info/top_level.txt
python_inflector-0.0.12.dist-info/RECORD
